gpio_calculator/__init__.py
gpio_calculator/calculator/__init__.py
gpio_calculator/calculator/test/__init__.py
gpio_calculator/calculator/test/calculator_test.py
GPIO_Calculator-1.0.2.dist-info/METADATA
GPIO_Calculator-1.0.2.dist-info/WHEEL
GPIO_Calculator-1.0.2.dist-info/top_level.txt
GPIO_Calculator-1.0.2.dist-info/RECORD
