Metadata-Version: 2.1
Name: GPIO-Calculator
Version: 1.0.2
Summary: Simple GPIO calculator for libgpiod based on its chardev.
Home-page: https://github.com/yeyeto2788/GPIO_Calculator
Author: Juan Biondi
Author-email: juanernestobiondi@gmail.com
License: MIT
Platform: UNKNOWN
Classifier: License :: OSI Approved :: MIT License
Classifier: Programming Language :: Python
Classifier: Programming Language :: Python :: 3
Classifier: Programming Language :: Python :: 3.4
Requires-Python: >=3.4.0
